mnb/__init__.py
mnb/mnb.py
MNB_soap-0.1.dist-info/LICENSE
MNB_soap-0.1.dist-info/METADATA
MNB_soap-0.1.dist-info/WHEEL
MNB_soap-0.1.dist-info/top_level.txt
MNB_soap-0.1.dist-info/RECORD
